spiffetls/__init__.py
spiffetls/context.py
spiffetls/dial.py
spiffetls/errors.py
spiffetls/listen.py
spiffetls/mode.py
spiffetls/tlsconfig/__init__.py
spiffetls/tlsconfig/authorize.py
spiffe_tls-0.2.2.dist-info/METADATA
spiffe_tls-0.2.2.dist-info/WHEEL
spiffe_tls-0.2.2.dist-info/licenses/LICENSE
spiffe_tls-0.2.2.dist-info/RECORD
