Metadata-Version: 2.4
Name: spiffe-tls
Version: 0.2.2
Summary: TLS Support using SPIFFE
License: Apache-2.0
License-File: LICENSE
Author: Max Lambrecht
Author-email: maxlambrecht@gmail.com
Requires-Python: >=3.10,<4.0
Classifier: License :: OSI Approved :: Apache Software License
Classifier: Programming Language :: Python :: 3
Classifier: Programming Language :: Python :: 3.10
Classifier: Programming Language :: Python :: 3.11
Classifier: Programming Language :: Python :: 3.12
Classifier: Programming Language :: Python :: 3.13
Classifier: Programming Language :: Python :: 3.14
Requires-Dist: pyOpenSSL (>=24,<26)
Requires-Dist: spiffe (>=0.2.3,<0.3.0)
Project-URL: Repository, https://github.com/HewlettPackard/py-spiffe
